{
    "ID": 175,
    "post_title": "Illo provident repellendus soluta dolor",
    "post_content": "<p>Est omnis fugit qui aut. Quibusdam vel excepturi officia optio similique. Sequi quo facere et. Similique possimus impedit deleniti et dicta. Qui vero quos repellendus molestiae. Quo deleniti tempore dolores nulla consequatur consequatur nemo. Accusamus qui incidunt quo rerum quas ut et. Quia molestiae debitis nulla repudiandae sit dolores nulla natus. Cumque et modi aliquid perspiciatis nulla. Sapiente perspiciatis et vero enim quam debitis temporibus est. Molestiae voluptatem consequuntur totam quaerat eaque ad cumque. Doloribus voluptates voluptas dolorem labore. Aut ea et voluptas sed. Enim maiores vel qui est aperiam nulla. Iure laborum ea praesentium et. Ut autem porro adipisci possimus.</p>\n<p>Veritatis reprehenderit provident qui. Ut veritatis consequatur ex recusandae quos. Impedit autem exercitationem voluptas ut non. Veritatis atque architecto. quia vel odit. ut ut suscipit ratione. Iusto quo id illo vel autem. Voluptatem deserunt tempore rem ad vitae amet Omnis accusamus <a title=\"Dignissimos ratione voluptatibus perferendis quis.\" href=\"http://morar.org/ad-iure-eaque-et-repellendus-dolores-laboriosam\">libero et omnis at. Aperiam</a> <a title=\"Qui dolorum id eum et ullam.\" href=\"http://www.witting.com/itaque-iure-numquam-sequi-quidem.html\">architecto temporibus ut porro</a> Hic nam deleniti officiis. Ut id explicabo voluptatem quos. eligendi placeat rem quos. Ullam tempore nihil alias sint ex. Nemo nostrum minima provident. Perferendis architecto qui rerum omnis omnis Ut ex quod numquam aliquam autem. Temporibus consectetur tenetur laborum. sint nemo optio deserunt quisquam. molestias saepe sed doloremque non nisi.</p>\n<h4>Est dolores recusandae deserunt quae. Sit optio nostrum voluptate alias ut sed voluptatem. Rerum autem eos veniam</h4>\n<ul><li>Est totam aut dolor</li><li>Error</li><li>Eum asperiores</li><li>Provident</li><li>Consequatur</li><li>Quo rerum nemo enim repellendus</li></ul>\n<!--more-->\n<h2>Eveniet magni fuga eos ab in. Est omnis voluptatum nemo. Temporibus debitis quia cum ea</h2>\n<ol><li>Voluptas velit harum occaecati doloremque fuga</li><li>Placeat</li><li>Ducimus inventore nostrum officiis ut doloribus</li></ol>\n<h3>Id aut asperiores dolor error. Beatae perferendis distinctio et vitae voluptatem magni</h3>\n<ol><li>Et molestiae</li><li>Cupiditate numquam quia qui fugiat</li><li>Ut eligendi atque iste explicabo</li><li>Quam omnis qui</li><li>Et dolorum</li><li>Autem officiis aut iusto maxime</li><li>Nulla ratione et iusto</li></ol>\n<h3>Aspernatur autem molestias et doloremque eum esse. Ex est vero optio eveniet</h3>\n<ul><li>Ipsam maxime sit eum</li><li>Non ipsum</li><li>Quo</li><li>Temporibus nemo nulla et</li><li>Dolorem dolores nihil fuga et nihil reiciendis</li><li>Et autem quisquam quibusdam</li><li>Ipsum totam nobis dolore</li></ul>\n<hr>",
    "post_excerpt": "",
    "post_type": "resource",
    "post_status": "publish",
    "post_name": "illo-provident-repellendus-soluta-dolor",
    "meta": {
        "fakerpress_flag": [
            "1"
        ],
        "_thumbnail_id": [
            {
                "invalid-image-mimetype": [
                    "Invalid image MimeType"
                ]
            }
        ]
    }
}